scanip/__init__.py
scanip/scanip.py
scanip-1.0.data/scripts/scanip.py
scanip-1.0.dist-info/DESCRIPTION.rst
scanip-1.0.dist-info/METADATA
scanip-1.0.dist-info/RECORD
scanip-1.0.dist-info/WHEEL
scanip-1.0.dist-info/metadata.json
scanip-1.0.dist-info/top_level.txt
