Metadata-Version: 2.0
Name: scanip
Version: 1.0
Summary: IP and MAC scanner
Home-page: UNKNOWN
Author: Vivek Bhardwaj
Author-email: vivek18pathak@gmail.com
License: UNKNOWN
Platform: linux-x86_64
Requires-Dist: scapy (==2.2.0.dev0)
